curvpyutils/__init__.py
curvpyutils/_version.py
curvpyutils/cli_util/__init__.py
curvpyutils/cli_util/cli_preparse.py
curvpyutils/cli_util/verbosity.py
curvpyutils/colors/__init__.py
curvpyutils/colors/ansi.py
curvpyutils/file_utils/__init__.py
curvpyutils/file_utils/dir_walker.py
curvpyutils/file_utils/fs_utils.py
curvpyutils/file_utils/hex_file_utils.py
curvpyutils/file_utils/open_write_iff_change.py
curvpyutils/file_utils/repo_utils.py
curvpyutils/logging/__init__.py
curvpyutils/logging/logger.py
curvpyutils/multi_progress/__init__.py
curvpyutils/multi_progress/display_options.py
curvpyutils/multi_progress/stacked_progress_table.py
curvpyutils/multi_progress/worker_progress_group.py
curvpyutils/shellutils/__init__.py
curvpyutils/shellutils/console.py
curvpyutils/shellutils/delta.py
curvpyutils/shellutils/which.py
curvpyutils/str_utils/__init__.py
curvpyutils/str_utils/insert_underscores.py
curvpyutils/system/__init__.py
curvpyutils/system/nprocs.py
curvpyutils/system/ulimits.py
curvpyutils/system/user_config_file.py
curvpyutils/test_helpers/__init__.py
curvpyutils/test_helpers/compare_files.py
curvpyutils/toml_utils/__init__.py
curvpyutils/toml_utils/canonicalizer.py
curvpyutils/toml_utils/combined_toml_dict.py
curvpyutils/toml_utils/merged_toml_dict.py
curvpyutils/toml_utils/toml_backend_rw.py
curvpyutils/tomlrw/__init__.py
curvpyutils/tomlrw/_canonicalizer.py
curvpyutils/tomlrw/tomlrw.py
curvpyutils/version_utils/__init__.py
curvpyutils/version_utils/version.py
curvpyutils-0.0.51.dist-info/METADATA
curvpyutils-0.0.51.dist-info/WHEEL
curvpyutils-0.0.51.dist-info/RECORD
