Metadata-Version: 2.4
Name: curvpyutils
Version: 0.0.51
Summary: Utility functions for Curv Python packages
Author: Mike Goelzer
License: MIT
Classifier: Programming Language :: Python :: 3 :: Only
Requires-Python: >=3.10
Requires-Dist: click>=8.1.0
Requires-Dist: importlib-metadata>=6.0.0
Requires-Dist: python-dotenv>=1.1.0
Requires-Dist: rich>=13
Requires-Dist: tomli-w
Requires-Dist: tomli; python_version < '3.11'
Provides-Extra: test
Requires-Dist: pytest-cov; extra == 'test'
Requires-Dist: pytest>=8; extra == 'test'
